tp2/verilog_tp2/assessment/src/tb_detector.v
`timescale 1ns/1ps

module tb_detector;

    // Entradas (Sinais que a câmera geraria)
    reg pix_clk;
    reg rgb_vs;
    reg rgb_de;
    reg [23:0] rgb_data;

    // Saídas (Sinal que vai para o ESP32)
    reg alerta_vazio;

    // Variáveis internas da nossa lógica
    reg [31:0] contador_fundo_pote;
    reg rgb_vs_prev;

    always @(posedge pix_clk) begin
        rgb_vs_prev <= rgb_vs;

        if (rgb_vs == 1'b1 && rgb_vs_prev == 1'b0) begin
            if (contador_fundo_pote > 5) begin // Meta reduzida para 5 no teste
                alerta_vazio <= 1'b1;
            end else begin
                alerta_vazio <= 1'b0;
            end
            contador_fundo_pote <= 0;
            
        end else if (rgb_de == 1'b1) begin
            if (rgb_data[15:8] > 8'd100) begin
                contador_fundo_pote <= contador_fundo_pote + 1;
            end
        end
    end
    
    // Gera um clock infinito (alterna a cada 10 nanosegundos)
    always #10 pix_clk = ~pix_clk;

    initial begin
        
        $dumpfile("onda_detector.vcd");
        $dumpvars(0, tb_detector);
        
        // 1. Zera tudo ao ligar
        pix_clk = 0; rgb_vs = 0; rgb_de = 0; rgb_data = 0;
        contador_fundo_pote = 0; alerta_vazio = 0; rgb_vs_prev = 0;

        $display("Iniciando Simulacao...");
        #100; // Espera um pouco

        // TESTE 1: FRAME CLARO (Pote Vazio -> Deve ligar o alerta)
        $display("Injetando pixels claros (Brilho 150)...");
        rgb_de = 1;
        rgb_data = {8'd0, 8'd150, 8'd0}; // Injeta brilho > 100
        #120; // Mantém por 6 clocks (O contador vai chegar a 6)
        rgb_de = 0; // Fim da imagem

        #50;
        $display("Enviando pulso VSYNC...");
        rgb_vs = 1; // Fim do quadro (Dispara a avaliação)
        #20;
        rgb_vs = 0;

        // TESTE 2: FRAME ESCURO (Dedo na lente -> Deve desligar o alerta)
        #100;
        $display("Injetando pixels escuros (Brilho 50)...");
        rgb_de = 1;
        rgb_data = {8'd0, 8'd150, 8'd0}; // Injeta 2 pixels claros
        #40;
        rgb_data = {8'd0, 8'd50, 8'd0};  // Cai para brilho escuro
        #80;  // Mantém os escuros por 4 clocks (Contador morre no 2)
        rgb_de = 0; // Fim da imagem

        #50;
        $display("Enviando pulso VSYNC...");
        rgb_vs = 1; // Fim do quadro (Dispara a avaliação)
        #20;
        rgb_vs = 0;

        #100;
        $display("Simulacao concluida.");
        $finish; // Encerra o teste
    end
endmodule

tp3/verilog_tp3/assessment/src/onda_detector.vcd
$date
	Wed May 27 22:27:51 2026
$end
$version
	Icarus Verilog
$end
$timescale
	1ps
$end
$scope module tb_detector $end
$var reg 1 ! alerta_vazio $end
$var reg 32 " contador_fundo_pote [31:0] $end
$var reg 1 # pix_clk $end
$var reg 24 $ rgb_data [23:0] $end
$var reg 1 % rgb_de $end
$var reg 1 & rgb_vs $end
$var reg 1 ' rgb_vs_prev $end
$upscope $end
$enddefinitions $end
$comment Show the parameter values. $end
$dumpall
$end
#0
$dumpvars
0'
0&
0%
b0 $
0#
b0 "
0!
$end
#10000
1#
#20000
0#
#30000
1#
#40000
0#
#50000
1#
#60000
0#
#70000
1#
#80000
0#
#90000
1#
#100000
0#
b1001011000000000 $
1%
#110000
b1 "
1#
#120000
0#
#130000
b10 "
1#
#140000
0#
#150000
b11 "
1#
#160000
0#
#170000
b100 "
1#
#180000
0#
#190000
b101 "
1#
#200000
0#
#210000
b110 "
1#
#220000
0#
0%
#230000
1#
#240000
0#
#250000
1#
#260000
0#
#270000
b0 "
1!
1'
1#
1&
#280000
0#
#290000
0'
1#
0&
#300000
0#
#310000
1#
#320000
0#
#330000
1#
#340000
0#
#350000
1#
#360000
0#
#370000
1#
#380000
0#
#390000
b1 "
1#
1%
#400000
0#
#410000
b10 "
1#
#420000
0#
#430000
1#
b11001000000000 $
#440000
0#
#450000
1#
#460000
0#
#470000
1#
#480000
0#
#490000
1#
#500000
0#
#510000
1#
0%
#520000
0#
#530000
1#
#540000
0#
#550000
1#
#560000
0#
1&
#570000
b0 "
0!
1'
1#
#580000
0#
0&
#590000
0'
1#
